{
  "project_info": {
    "project_number": "546125091168",
    "project_id": "flutter-chat-app-a195e",
    "storage_bucket": "flutter-chat-app-a195e.firebasestorage.app"
  },
  "client": [
    {
      "client_info": {
        "mobilesdk_app_id": "1:546125091168:android:08e4a2d88e577efb754e05",
        "android_client_info": {
          "package_name": "com.example.chat_app"
        }
      },
      "oauth_client": [],
      "api_key": [
        {
          "current_key": "AIzaSyBGmHvXZwKSOrlfjiKo3V7MNOEZy2YDuCY"
        }
      ],
      "services": {
        "appinvite_service": {
          "other_platform_oauth_client": []
        }
      }
    }
  ],
  "configuration_version": "1"
}